devart/quickbooks/__init__.py
devart/quickbooks/quickbooks.cp310-win_amd64.pyd
devart/quickbooks/quickbooks.pyi
devart/quickbooks/QuickBooks/Devart.Python.QuickBooksEngine.dll
devart/quickbooks/QuickBooks/sqlite3.dll
devart/quickbooks/sqlalchemy/__init__.py
devart_quickbooks_connector-1.2.0.dist-info/LICENSE
devart_quickbooks_connector-1.2.0.dist-info/METADATA
devart_quickbooks_connector-1.2.0.dist-info/WHEEL
devart_quickbooks_connector-1.2.0.dist-info/top_level.txt
devart_quickbooks_connector-1.2.0.dist-info/RECORD
